rdeploy/__init__.py
rdeploy/exceptions.py
rdeploy/main.py
rdeploy/tasks.py
rdeploy/utils.py
rdeploy-0.1.9.dist-info/LICENSE
rdeploy-0.1.9.dist-info/METADATA
rdeploy-0.1.9.dist-info/WHEEL
rdeploy-0.1.9.dist-info/entry_points.txt
rdeploy-0.1.9.dist-info/top_level.txt
rdeploy-0.1.9.dist-info/zip-safe
rdeploy-0.1.9.dist-info/RECORD
