Metadata-Version: 2.1
Name: rdeploy
Version: 0.1.9
Summary: CLI that makes it easy to build and deploy an application to k8s.
Home-page: https://github.com/rehive/rdeploy
Author: Rehive
Author-email: info@rehive.com
License: MIT License
Keywords: docker python helm kubernetes build automation deploy
Classifier: Development Status :: 4 - Beta
Classifier: Intended Audience :: System Administrators
Classifier: Topic :: Software Development :: Build Tools
Classifier: Topic :: System :: Installation/Setup
Classifier: Topic :: System :: Software Distribution
Classifier: Operating System :: OS Independent
Classifier: License :: OSI Approved :: MIT License
Classifier: Programming Language :: Python
Classifier: Programming Language :: Python :: 3
Classifier: Programming Language :: Python :: 3.6
License-File: LICENSE
Requires-Dist: invoke (==0.18.1)
Requires-Dist: kubernetes (==21.7.0)
Requires-Dist: packaging (~=20.9)
Requires-Dist: python-dotenv (==00.19.2)
Requires-Dist: PyYAML (==6.0)
Requires-Dist: semver (==2.13.0)
Requires-Dist: requests (==2.26.0)
Provides-Extra: dev
Requires-Dist: invoke (==0.18.1) ; extra == 'dev'
Requires-Dist: kubernetes (==21.7.0) ; extra == 'dev'
Requires-Dist: packaging (~=20.9) ; extra == 'dev'
Requires-Dist: python-dotenv (==00.19.2) ; extra == 'dev'
Requires-Dist: PyYAML (==6.0) ; extra == 'dev'
Requires-Dist: semver (==2.13.0) ; extra == 'dev'
Requires-Dist: requests (==2.26.0) ; extra == 'dev'
Provides-Extra: test
Requires-Dist: coverage ; extra == 'test'
